ixontray-0.5.6.dist-info/METADATA
ixontray-0.5.6.dist-info/WHEEL
ixontray-0.5.6.dist-info/entry_points.txt
ixontray/.idea/inspectionProfiles/profiles_settings.xml
ixontray/.idea/ixontray.iml
ixontray/.idea/misc.xml
ixontray/.idea/modules.xml
ixontray/.idea/vcs.xml
ixontray/.idea/workspace.xml
ixontray/__init__.py
ixontray/base_model_store.py
ixontray/commands-windows.yaml
ixontray/commands.yaml
ixontray/config.py
ixontray/icon.png
ixontray/icon_not_connected.png
ixontray/install.sh
ixontray/ixon_cloud_api.py
ixontray/ixon_tray.py
ixontray/ixon_vpn_client_api.py
ixontray/launcher.py
ixontray/settings_window.py
ixontray/telemetry.py
ixontray/types/__init__.py
ixontray/types/api.py
ixontray/types/common.py
ixontray/update.py
ixontray-0.5.6.dist-info/RECORD
