Metadata-Version: 2.1
Name: ixontray
Version: 0.5.6
Summary: A tray application and launcher to connect to remote systems using IXON
Keywords: tool,ixon
Author-Email: Mart Moerdijk <mart@mmoerdijk.nl>
License: BSD
Requires-Python: >=3.10
Requires-Dist: PyQt6
Requires-Dist: pydantic
Requires-Dist: icecream
Requires-Dist: requests
Requires-Dist: ruamel.yaml
Requires-Dist: keyring
Requires-Dist: pypi-json>=0.4.0
Requires-Dist: packaging>=23.2
Requires-Dist: sentry-sdk>=2.19.2
